[
	{
		"id":"99463127",
		"HW1":"100%",
		"HW2":"100%",
		"HW3":"100%"
	},
	{
		"id":"99463131",
		"HW1":"100%",
		"HW2":"100%",
		"HW3":"100%"
	},
	{
		"id":"99463124",
		"HW1":"100%",
		"HW2":"100%",
		"HW3":"100%"
	},
	{
		"id":"99463122",
		"HW1":"100%",
		"HW2":"95%"
	},
	{
		"id":"99463133",
		"HW1":"100%",
		"HW2":"70%",
		"HW3":"100%"
	},
	{
		"id":"99463180",
		"HW1":"100%",
		"HW2":"100%",
		"HW3":"100%"
	},
	{
		"id":"99463184",
		"HW1":"100%",
		"HW2":"100%",
		"HW3":"90%"
	},
	{
		"id":"99463160",
		"HW1":"100%",
		"HW2":"100%",
		"HW3":"100%"
	},
	{
		"id":"400463101",
		"HW1":"100%",
		"HW2":"100%",
		"HW3":"100%"
	},
	{
		"id":"99463134",
		"HW1":"100%",
		"HW2":"100%",
		"HW3":"100%"
	},
	{
		"id":"99463157",
		"HW1":"100%",
		"HW2":"100%",
		"HW3":"100%"
	},
	{
		"id":"99463147",
		"HW1":"100%",
		"HW2":"100%",
		"HW3":"100%"
	},
	{
		"id":"98463149",
		"HW1":"100%",
		"HW2":"100%"
	},
	{
		"id":"98463115",
		"HW1":"100%",
		"HW2":"90%",
		"HW3":"100%"
	},
	{
		"id":"99463136",
		"HW1":"100%",
		"HW2":"100%"
	},
	{
		"id":"99463168",
		"HW1":"100%",
		"HW2":"100%",
		"HW3":"95%"
	},
	{
		"id":"98548121",
		"HW1":"100%",
		"HW2":"100%",
		"HW3":"80%"
	},
	{
		"id":"98463114",
		"HW1":"100%",
		"HW2":"90%"
	},
	{
		"id":"99463156",
		"HW1":"100%",
		"HW2":"100%",
		"HW3":"100%"
	},
	{
		"id":"99463152",
		"HW1":"100%",
		"HW2":"90%",
		"HW3":"100%"
	},
	{
		"id":"99463155",
		"HW1":"100%",
		"HW2":"99%",
		"HW3":"60%"
	},
	{
		"id":"99463146",
		"HW1":"100%",
		"HW2":"100%",
		"HW3":"100%"
	},
	{
		"id":"99463199",
		"HW1":"100%",
		"HW2":"100%",
		"HW3":"95%"
	},
	{
		"id":"99463167",
		"HW1":"100%",
		"HW2":"100%",
		"HW3":"100%"
	},
	{
		"id":"99463172",
		"HW1":"100%"
	},
	{
		"id":"99463166",
		"HW1":"90%",
		"HW2":"100%"
	},
	{
		"id":"99463119",
		"HW1":"70%"
	},
	{
		"id":"99463132",
		"HW1":"100%",
		"HW2":"100%",
		"HW3":"100%"
	},
	{
		"id":"97463154",
		"HW1":"70%",
		"HW2":"90%"
	},
	{
		"id":"99463107",
		"HW1":"100%",
		"HW2":"100%",
		"HW3":"100%"
	},
	{
		"id":"99463143",
		"HW1":"100%",
		"HW2":"100%",
		"HW3":"100%"
	},
	{
		"id":"99463175",
		"HW1":"100%",
		"Hw2":"60%"
	},
	{
		"id":"99463108",
		"HW1":"100%",
		"HW2":"90%",
		"HW3":"100%"
	},
	{
		"id":"97463102",
		"HW2":"100%",
		"HW3":"90%"
	},
	{
		"id":"99463162",
		"HW2":"100%",
		"HW3":"100%"
	},
	{
		"id":"99463138",
		"HW2":"100%"
	},
	{
		"id":"99463148",
		"HW2":"100%",
		"HW3":"100%"
	},
	{
		"id":"99463153",
		"HW1":"100%",
		"HW2":"100%",
		"HW3":"100%"
	},
	{
		"id":"99463101",
		"HW3":"100%"
	},
	{
		"id":"99463181",
		"HW3":"100%"
	}
]